odoo10_addon_business_requirement_deliverable-10.0.1.0.0-py2.7-nspkg.pth
odoo/addons/business_requirement_deliverable/README.rst
odoo/addons/business_requirement_deliverable/__init__.py
odoo/addons/business_requirement_deliverable/__manifest__.py
odoo/addons/business_requirement_deliverable/data/br_report_paperformat.xml
odoo/addons/business_requirement_deliverable/data/business_requirement_deliverable_demo.xml
odoo/addons/business_requirement_deliverable/i18n/sl.po
odoo/addons/business_requirement_deliverable/models/__init__.py
odoo/addons/business_requirement_deliverable/models/business.py
odoo/addons/business_requirement_deliverable/models/res_partner.py
odoo/addons/business_requirement_deliverable/report/__init__.py
odoo/addons/business_requirement_deliverable/report/br_deliverable_report.py
odoo/addons/business_requirement_deliverable/report/br_deliverable_report_view.xml
odoo/addons/business_requirement_deliverable/report/br_deliverable_sale_report.py
odoo/addons/business_requirement_deliverable/report/br_deliverable_sale_report_view.xml
odoo/addons/business_requirement_deliverable/report/report.xml
odoo/addons/business_requirement_deliverable/security/business_requirement_deliverable_security.xml
odoo/addons/business_requirement_deliverable/security/ir.model.access.csv
odoo/addons/business_requirement_deliverable/static/description/icon.png
odoo/addons/business_requirement_deliverable/static/img/bus_req_deliverable.png
odoo/addons/business_requirement_deliverable/static/img/bus_req_deliverable2.png
odoo/addons/business_requirement_deliverable/static/img/bus_req_report1.png
odoo/addons/business_requirement_deliverable/static/img/bus_req_report2.png
odoo/addons/business_requirement_deliverable/static/img/bus_req_report3.png
odoo/addons/business_requirement_deliverable/static/img/bus_req_resource.png
odoo/addons/business_requirement_deliverable/tests/__init__.py
odoo/addons/business_requirement_deliverable/tests/test_br.py
odoo10_addon_business_requirement_deliverable-10.0.1.0.0.dist-info/DESCRIPTION.rst
odoo10_addon_business_requirement_deliverable-10.0.1.0.0.dist-info/METADATA
odoo10_addon_business_requirement_deliverable-10.0.1.0.0.dist-info/RECORD
odoo10_addon_business_requirement_deliverable-10.0.1.0.0.dist-info/WHEEL
odoo10_addon_business_requirement_deliverable-10.0.1.0.0.dist-info/metadata.json
odoo10_addon_business_requirement_deliverable-10.0.1.0.0.dist-info/namespace_packages.txt
odoo10_addon_business_requirement_deliverable-10.0.1.0.0.dist-info/top_level.txt
